{
  "3": {
    "inputs": {
      "seed": 0,
      "steps": 25,
      "cfg": 6,
      "sampler_name": "euler_ancestral",
      "scheduler": "karras",
      "denoise": 1,
      "model": [
        "4",
        0
      ],
      "positive": [
        "6",
        0
      ],
      "negative": [
        "7",
        0
      ],
      "latent_image": [
        "5",
        0
      ]
    },
    "class_type": "KSampler",
    "_meta": {
      "title": "KSampler"
    }
  },
  "4": {
    "inputs": {
      "ckpt_name": "dreamshaper_5BakedVae.safetensors"
    },
    "class_type": "CheckpointLoaderSimple",
    "_meta": {
      "title": "Load Checkpoint"
    }
  },
  "5": {
    "inputs": {
      "width": 1024,
      "height": 1024,
      "batch_size": 1
    },
    "class_type": "EmptyLatentImage",
    "_meta": {
      "title": "Empty Latent Image"
    }
  },
  "6": {
    "inputs": {
      "text": "A surreal digital artwork merges Art Nouveau with Japanese ukiyo-e woodblock print aesthetics, portraying an enigmatic creature reminiscent of a phoenix, composed of tender cherry blossom petals in their prime. The ethereal being gracefully glides above the skyline during sunset, its luminous presence bathing the towering glass and steel structures below in a tapestry of warm pink and orange hues. As it drifts over a lively street market thronged with people, the phoenix`s wings trace an ephemeral path of blossoming flowers that sway gently amidst the soft evening air, invoking a sense of both awe and longing for transient memories. This distinctive blend of nature and technology encapsulates a fleeting moment of loveliness in a world perpetually undergoing transformation.",
      "clip": [
        "4",
        1
      ]
    },
    "class_type": "CLIPTextEncode",
    "_meta": {
      "title": "CLIP Text Encode (Prompt)"
    }
  },
  "7": {
    "inputs": {
      "text": "",
      "clip": [
        "4",
        1
      ]
    },
    "class_type": "CLIPTextEncode",
    "_meta": {
      "title": "CLIP Text Encode (Prompt)"
    }
  },
  "8": {
    "inputs": {
      "samples": [
        "3",
        0
      ],
      "vae": [
        "4",
        2
      ]
    },
    "class_type": "VAEDecode",
    "_meta": {
      "title": "VAE Decode"
    }
  },
  "9": {
    "inputs": {
      "filename_prefix": "ComfyUI",
      "images": [
        "8",
        0
      ]
    },
    "class_type": "SaveImage",
    "_meta": {
      "title": "Save Image"
    }
  }
}